cryoswath/.gitignore
cryoswath/__init__.py
cryoswath/config.ini
cryoswath/gis.py
cryoswath/l1b.py
cryoswath/l2.py
cryoswath/l3.py
cryoswath/l4.py
cryoswath/misc.py
cryoswath/test_plots/__init__.py
cryoswath/test_plots/maps.py
cryoswath/test_plots/timeseries.py
cryoswath/test_plots/waveform.py
cryoswath-0.2.4.dist-info/entry_points.txt
cryoswath-0.2.4.dist-info/licenses/LICENSE.txt
cryoswath-0.2.4.dist-info/WHEEL
cryoswath-0.2.4.dist-info/METADATA
cryoswath-0.2.4.dist-info/RECORD
