Metadata-Version: 2.4
Name: cryoswath
Version: 0.2.4
Summary: Swath processing toolbox for CryoSat-2
Keywords: glacier,altimetry,swath,cryosat
Author-email: Jan Haacker <j.m.haacker@tudelft.nl>
Requires-Python: >=3.11
Classifier: Programming Language :: Python :: 3
Classifier: Operating System :: OS Independent
Classifier: License :: OSI Approved :: MIT License
License-File: LICENSE.txt
Requires-Dist: Bottleneck
Requires-Dist: dask
Requires-Dist: defusedxml
Requires-Dist: geopandas>=1.0.1
Requires-Dist: gitpython
Requires-Dist: h5netcdf
Requires-Dist: h5py
Requires-Dist: matplotlib
Requires-Dist: numpy
Requires-Dist: packaging
Requires-Dist: pandas
Requires-Dist: pyarrow
Requires-Dist: pyogrio
Requires-Dist: pyproj
Requires-Dist: pystac_client
Requires-Dist: python-dateutil
Requires-Dist: rasterio
Requires-Dist: rioxarray
Requires-Dist: scikit-learn
Requires-Dist: scipy
Requires-Dist: shapely
Requires-Dist: stackstac
Requires-Dist: statsmodels
Requires-Dist: tables
Requires-Dist: tqdm
Requires-Dist: xarray
Requires-Dist: zarr
Requires-Dist: cryoswath[dev, docs, notebooks] ; extra == "all"
Requires-Dist: flit ; extra == "dev"
Requires-Dist: pip-compile ; extra == "dev"
Requires-Dist: ruff ; extra == "dev"
Requires-Dist: sphinx ; extra == "docs"
Requires-Dist: sphinx-rtd-theme ; extra == "docs"
Requires-Dist: ipykernel ; extra == "notebooks"
Project-URL: Documentation, https://cryoswath.readthedocs.io/
Project-URL: Issues, https://github.com/j-haacker/cryoswath/issues
Project-URL: Repository, https://github.com/j-haacker/cryoswath.git
Provides-Extra: all
Provides-Extra: dev
Provides-Extra: docs
Provides-Extra: notebooks
